scada/__init__.py
scada/si_scada.py
scada/models/__init__.py
scada/models/wdgrl.py
scada/models/wdgrl_reducelr.py
scada/solveinequalities/__init__.py
scada/solveinequalities/setup.py
scada/utils/__init__.py
scada/utils/construct_interval.py
scada/utils/kmeans.py
scada/utils/util.py
scada_python-0.1.2.dist-info/licenses/LICENSE
scada_python-0.1.2.dist-info/METADATA
scada_python-0.1.2.dist-info/WHEEL
scada_python-0.1.2.dist-info/top_level.txt
scada_python-0.1.2.dist-info/RECORD
