Metadata-Version: 2.4
Name: scada-python
Version: 0.1.2
Summary: Statistical Inference for k-means Clustering after Domain Adaptation
Author-email: locluklak <23520854@uit.edu.vn>
Project-URL: Homepage, https://github.com/DAIR-Group/SCaDA
Requires-Python: >=3.10
License-File: LICENSE
Requires-Dist: numpy
Requires-Dist: pandas
Requires-Dist: mpmath
Requires-Dist: torch
Requires-Dist: scikit-learn
Requires-Dist: PyYAML
Requires-Dist: tqdm
Dynamic: license-file
